Metadata-Version: 2.1
Name: grpc-powergate-client
Version: 2.6.2
Summary: UNKNOWN
Home-page: https://github.com/textileio/powergate
Author: Textile
Author-email: contact@textile.io
License: UNKNOWN
Platform: UNKNOWN
Requires-Dist: protobuf
Requires-Dist: grpcio
